allthedots
