Metadata-Version: 1.0
Name: allthedots
Version: 0.1.9
Summary: Make a list of important stuff.
Home-page: https://github.com/cjrk/AllTheDots
Author: Christian Jurke
Author-email: christian.jurke@gmail.com
License: UNKNOWN
Platform: UNKNOWN
